genaitopic/__init__.py
genaitopic/listthemes/__init__.py
genaitopic/listthemes/finalthemes.py
genaitopic/listthemes/stratoboostthemes.py
genaitopic/listthemes/stratoboostthemes_domain.py
genaitopic/metrics/ARI_NMI_HarmonicPurity.py
genaitopic/metrics/__init__.py
genaitopic/metrics/similarity_score.py
genaitopic/predict/ChromaRagPredict.py
genaitopic/predict/FaissRagPredict.py
genaitopic/predict/FastFaissRagPredict.py
genaitopic/predict/__init__.py
genaitopic/sampling/__init__.py
genaitopic/sampling/stratoboost.py
genaitopic/sampling/stratobooststring.py
genaitopic-0.1.9.dist-info/METADATA
genaitopic-0.1.9.dist-info/WHEEL
genaitopic-0.1.9.dist-info/top_level.txt
genaitopic-0.1.9.dist-info/RECORD
