Metadata-Version: 2.2
Name: genaitopic
Version: 0.1.9
Summary: A package for auto topic generation and prediction using RAG & LLMs.
Author: Vishal Jadhav
Author-email: vishalsjadhav53@gmail.com
Classifier: Programming Language :: Python :: 3
Classifier: License :: OSI Approved :: MIT License
Requires-Dist: pandas
Requires-Dist: scikit-learn
Requires-Dist: langchain
Requires-Dist: datetime
Dynamic: author
Dynamic: author-email
Dynamic: classifier
Dynamic: description
Dynamic: description-content-type
Dynamic: requires-dist
Dynamic: summary
